{
  "total_coins": 3521,
  "start_coin": 3521,
  "coins_per_hour": 0.0,
  "coins_today": 0,
  "today_date": "2026-03-12",
  "last_updated": "2026-03-12 08:06:30",
  "logs": [
    "08:06:30 - ⏳ Chờ coin... (3521)",
    "08:05:29 - ⏳ Chờ coin... (3521)",
    "08:04:29 - ⏳ Chờ coin... (3521)",
    "08:03:28 - ⏳ Chờ coin... (3521)",
    "08:02:27 - ⏳ Chờ coin... (3521)",
    "08:01:26 - ⏳ Chờ coin... (3521)",
    "08:00:26 - ⏳ Chờ coin... (3521)",
    "07:59:25 - ⏳ Chờ coin... (3521)",
    "07:58:24 - ⏳ Chờ coin... (3521)",
    "07:57:23 - ⏳ Chờ coin... (3521)",
    "07:56:22 - ⏳ Chờ coin... (3521)",
    "07:55:22 - ⏳ Chờ coin... (3521)",
    "07:54:21 - ⏳ Chờ coin... (3521)",
    "07:53:20 - ⏳ Chờ coin... (3521)",
    "07:52:20 - ⏳ Chờ coin... (3521)",
    "07:51:19 - ⏳ Chờ coin... (3521)",
    "07:50:18 - ⏳ Chờ coin... (3521)",
    "07:49:17 - ⏳ Chờ coin... (3521)",
    "07:48:17 - ⏳ Chờ coin... (3521)",
    "07:47:16 - ⏳ Chờ coin... (3521)",
    "07:46:15 - ⏳ Chờ coin... (3521)",
    "07:45:14 - ⏳ Chờ coin... (3521)",
    "07:44:13 - ⏳ Chờ coin... (3521)",
    "07:43:13 - ⏳ Chờ coin... (3521)",
    "07:42:12 - ⏳ Chờ coin... (3521)",
    "07:41:11 - ⏳ Chờ coin... (3521)",
    "07:40:10 - ⏳ Chờ coin... (3521)",
    "07:39:09 - ⏳ Chờ coin... (3521)",
    "07:38:09 - ⏳ Chờ coin... (3521)",
    "07:37:08 - ⏳ Chờ coin... (3521)",
    "07:36:07 - ⏳ Chờ coin... (3521)",
    "07:35:06 - ⏳ Chờ coin... (3521)",
    "07:34:06 - ⏳ Chờ coin... (3521)",
    "07:33:05 - ⏳ Chờ coin... (3521)",
    "07:32:04 - ⏳ Chờ coin... (3521)",
    "07:31:04 - ⏳ Chờ coin... (3521)",
    "07:30:03 - ⏳ Chờ coin... (3521)",
    "07:29:02 - ⏳ Chờ coin... (3521)",
    "07:28:01 - ⏳ Chờ coin... (3521)",
    "07:27:01 - ⏳ Chờ coin... (3521)",
    "07:26:00 - ⏳ Chờ coin... (3521)",
    "07:24:59 - ⏳ Chờ coin... (3521)",
    "07:23:58 - ⏳ Chờ coin... (3521)",
    "07:22:58 - ⏳ Chờ coin... (3521)",
    "07:21:57 - ⏳ Chờ coin... (3521)",
    "07:20:56 - ⏳ Chờ coin... (3521)",
    "07:19:55 - ⏳ Chờ coin... (3521)",
    "07:18:55 - ⏳ Chờ coin... (3521)",
    "07:17:54 - ⏳ Chờ coin... (3521)",
    "07:16:53 - ⏳ Chờ coin... (3521)"
  ]
}