{
  "total_coins": 7146,
  "start_coin": 7146,
  "coins_per_hour": 0.0,
  "coins_today": 0,
  "today_date": "2026-03-29",
  "last_updated": "2026-03-29 07:20:07",
  "logs": [
    "07:20:07 - ⏳ Chờ coin... (7146)",
    "07:19:07 - ⏳ Chờ coin... (7146)",
    "07:18:06 - ⏳ Chờ coin... (7146)",
    "07:17:05 - ⏳ Chờ coin... (7146)",
    "07:16:05 - ⏳ Chờ coin... (7146)",
    "07:15:04 - ⏳ Chờ coin... (7146)",
    "07:14:04 - ⏳ Chờ coin... (7146)",
    "07:13:03 - ⏳ Chờ coin... (7146)",
    "07:12:02 - ⏳ Chờ coin... (7146)",
    "07:11:02 - ⏳ Chờ coin... (7146)",
    "07:10:01 - ⏳ Chờ coin... (7146)",
    "07:09:01 - ⏳ Chờ coin... (7146)",
    "07:08:00 - ⏳ Chờ coin... (7146)",
    "07:06:59 - ⏳ Chờ coin... (7146)",
    "07:05:59 - ⏳ Chờ coin... (7146)",
    "07:04:58 - ⏳ Chờ coin... (7146)",
    "07:03:58 - ⏳ Chờ coin... (7146)",
    "07:02:57 - ⏳ Chờ coin... (7146)",
    "07:01:57 - ⏳ Chờ coin... (7146)",
    "07:00:56 - ⏳ Chờ coin... (7146)",
    "06:59:56 - ⏳ Chờ coin... (7146)",
    "06:58:55 - ⏳ Chờ coin... (7146)",
    "06:57:54 - ⏳ Chờ coin... (7146)",
    "06:56:54 - ⏳ Chờ coin... (7146)",
    "06:55:53 - ⏳ Chờ coin... (7146)",
    "06:54:53 - ⏳ Chờ coin... (7146)",
    "06:53:52 - ⏳ Chờ coin... (7146)",
    "06:52:52 - ⏳ Chờ coin... (7146)",
    "06:51:51 - ⏳ Chờ coin... (7146)",
    "06:50:51 - ⏳ Chờ coin... (7146)",
    "06:49:50 - ⏳ Chờ coin... (7146)",
    "06:48:49 - ⏳ Chờ coin... (7146)",
    "06:47:49 - ⏳ Chờ coin... (7146)",
    "06:46:48 - ⏳ Chờ coin... (7146)",
    "06:45:48 - ⏳ Chờ coin... (7146)",
    "06:44:47 - ⏳ Chờ coin... (7146)",
    "06:43:46 - ⏳ Chờ coin... (7146)",
    "06:42:46 - ⏳ Chờ coin... (7146)",
    "06:41:45 - ⏳ Chờ coin... (7146)",
    "06:40:45 - ⏳ Chờ coin... (7146)",
    "06:39:44 - ⏳ Chờ coin... (7146)",
    "06:38:43 - ⏳ Chờ coin... (7146)",
    "06:37:43 - ⏳ Chờ coin... (7146)",
    "06:36:42 - ⏳ Chờ coin... (7146)",
    "06:35:42 - ⏳ Chờ coin... (7146)",
    "06:34:41 - ⏳ Chờ coin... (7146)",
    "06:33:40 - ⏳ Chờ coin... (7146)",
    "06:32:40 - ⏳ Chờ coin... (7146)",
    "06:31:39 - ⏳ Chờ coin... (7146)",
    "06:30:39 - ⏳ Chờ coin... (7146)"
  ]
}