{
  "total_coins": 10666,
  "start_coin": 10666,
  "coins_per_hour": 0.0,
  "coins_today": 0,
  "today_date": "2026-03-19",
  "last_updated": "2026-03-19 17:58:42",
  "logs": [
    "17:58:42 - ⏳ Chờ coin... (10666)",
    "17:57:41 - ⏳ Chờ coin... (10666)",
    "17:56:39 - ⏳ Chờ coin... (10666)",
    "17:55:30 - ⏳ Chờ coin... (10666)",
    "17:54:20 - ⏳ Chờ coin... (10666)",
    "17:53:19 - ⏳ Chờ coin... (10666)",
    "17:52:17 - ⏳ Chờ coin... (10666)",
    "17:51:06 - ⏳ Chờ coin... (10666)",
    "17:50:04 - ⏳ Chờ coin... (10666)",
    "17:48:50 - ⏳ Chờ coin... (10666)",
    "17:47:46 - ⏳ Chờ coin... (10666)",
    "17:46:44 - ⏳ Chờ coin... (10666)",
    "17:45:41 - ⏳ Chờ coin... (10666)",
    "17:44:33 - ⏳ Chờ coin... (10666)",
    "17:43:24 - ⏳ Chờ coin... (10666)",
    "17:42:21 - ⏳ Chờ coin... (10666)",
    "17:41:18 - ⏳ Chờ coin... (10666)",
    "17:40:10 - ⏳ Chờ coin... (10666)",
    "17:39:07 - ⏳ Chờ coin... (10666)",
    "17:38:05 - ⏳ Chờ coin... (10666)",
    "17:36:57 - ⏳ Chờ coin... (10666)",
    "17:35:55 - ⏳ Chờ coin... (10666)",
    "17:34:54 - ⏳ Chờ coin... (10666)",
    "17:33:45 - ⏳ Chờ coin... (10666)",
    "17:32:43 - ⏳ Chờ coin... (10666)",
    "17:31:42 - ⏳ Chờ coin... (10666)",
    "17:30:39 - ⏳ Chờ coin... (10666)",
    "17:29:38 - ⏳ Chờ coin... (10666)",
    "17:28:37 - ⏳ Chờ coin... (10666)",
    "17:27:36 - ⏳ Chờ coin... (10666)",
    "17:26:35 - ⏳ Chờ coin... (10666)",
    "17:25:35 - ⏳ Chờ coin... (10666)",
    "17:24:34 - ⏳ Chờ coin... (10666)",
    "17:23:33 - ⏳ Chờ coin... (10666)",
    "17:22:32 - ⏳ Chờ coin... (10666)",
    "17:21:31 - ⏳ Chờ coin... (10666)",
    "17:20:30 - ⏳ Chờ coin... (10666)",
    "17:19:29 - ⏳ Chờ coin... (10666)",
    "17:18:28 - ⏳ Chờ coin... (10666)",
    "17:17:27 - ⏳ Chờ coin... (10666)",
    "17:16:26 - ⏳ Chờ coin... (10666)",
    "17:15:25 - ⏳ Chờ coin... (10666)",
    "17:14:24 - ⏳ Chờ coin... (10666)",
    "17:13:23 - ⏳ Chờ coin... (10666)",
    "17:12:22 - ⏳ Chờ coin... (10666)",
    "17:11:21 - ⏳ Chờ coin... (10666)",
    "17:10:20 - ⏳ Chờ coin... (10666)",
    "17:09:19 - ⏳ Chờ coin... (10666)",
    "17:08:18 - ⏳ Chờ coin... (10666)",
    "17:07:17 - ⏳ Chờ coin... (10666)"
  ]
}