{
  "total_coins": 10071,
  "start_coin": 10071,
  "coins_per_hour": 0.0,
  "coins_today": 0,
  "today_date": "2026-03-19",
  "last_updated": "2026-03-19 08:23:21",
  "logs": [
    "08:23:21 - ⏳ Chờ coin... (10071)",
    "08:22:21 - ⏳ Chờ coin... (10071)",
    "08:21:20 - ⏳ Chờ coin... (10071)",
    "08:20:19 - ⏳ Chờ coin... (10071)",
    "08:19:19 - ⏳ Chờ coin... (10071)",
    "08:18:18 - ⏳ Chờ coin... (10071)",
    "08:17:17 - ⏳ Chờ coin... (10071)",
    "08:16:16 - ⏳ Chờ coin... (10071)",
    "08:15:16 - ⏳ Chờ coin... (10071)",
    "08:14:15 - ⏳ Chờ coin... (10071)",
    "08:13:14 - ⏳ Chờ coin... (10071)",
    "08:12:13 - ⏳ Chờ coin... (10071)",
    "08:11:13 - ⏳ Chờ coin... (10071)",
    "08:10:12 - ⏳ Chờ coin... (10071)",
    "08:09:11 - ⏳ Chờ coin... (10071)",
    "08:08:11 - ⏳ Chờ coin... (10071)",
    "08:07:10 - ⏳ Chờ coin... (10071)",
    "08:06:09 - ⏳ Chờ coin... (10071)",
    "08:05:08 - ⏳ Chờ coin... (10071)",
    "08:04:08 - ⏳ Chờ coin... (10071)",
    "08:03:07 - ⏳ Chờ coin... (10071)",
    "08:02:06 - ⏳ Chờ coin... (10071)",
    "08:01:05 - ⏳ Chờ coin... (10071)",
    "08:00:05 - ⏳ Chờ coin... (10071)",
    "07:59:04 - ⏳ Chờ coin... (10071)",
    "07:58:03 - ⏳ Chờ coin... (10071)",
    "07:57:03 - ⏳ Chờ coin... (10071)",
    "07:56:02 - ⏳ Chờ coin... (10071)",
    "07:55:01 - ⏳ Chờ coin... (10071)",
    "07:54:00 - ⏳ Chờ coin... (10071)",
    "07:52:59 - ⏳ Chờ coin... (10071)",
    "07:51:59 - ⏳ Chờ coin... (10071)",
    "07:50:58 - ⏳ Chờ coin... (10071)",
    "07:49:57 - ⏳ Chờ coin... (10071)",
    "07:48:57 - ⏳ Chờ coin... (10071)",
    "07:47:56 - ⏳ Chờ coin... (10071)",
    "07:46:54 - ⏳ Chờ coin... (10071)",
    "07:45:54 - ⏳ Chờ coin... (10071)",
    "07:44:53 - ⏳ Chờ coin... (10071)",
    "07:43:52 - ⏳ Chờ coin... (10071)",
    "07:42:51 - ⏳ Chờ coin... (10071)",
    "07:41:51 - ⏳ Chờ coin... (10071)",
    "07:40:50 - ⏳ Chờ coin... (10071)",
    "07:39:49 - ⏳ Chờ coin... (10071)",
    "07:38:49 - ⏳ Chờ coin... (10071)",
    "07:37:48 - ⏳ Chờ coin... (10071)",
    "07:36:47 - ⏳ Chờ coin... (10071)",
    "07:35:47 - ⏳ Chờ coin... (10071)",
    "07:34:46 - ⏳ Chờ coin... (10071)",
    "07:33:45 - ⏳ Chờ coin... (10071)"
  ]
}