{
  "total_coins": 5241,
  "start_coin": 5241,
  "coins_per_hour": 0.0,
  "coins_today": 0,
  "today_date": "2026-03-13",
  "last_updated": "2026-03-13 14:20:41",
  "logs": [
    "14:20:41 - ⏳ Chờ coin... (5241)",
    "14:19:40 - ⏳ Chờ coin... (5241)",
    "14:18:39 - ⏳ Chờ coin... (5241)",
    "14:17:38 - ⏳ Chờ coin... (5241)",
    "14:16:37 - ⏳ Chờ coin... (5241)",
    "14:15:35 - ⏳ Chờ coin... (5241)",
    "14:14:34 - ⏳ Chờ coin... (5241)",
    "14:13:34 - ⏳ Chờ coin... (5241)",
    "14:12:33 - ⏳ Chờ coin... (5241)",
    "14:11:32 - ⏳ Chờ coin... (5241)",
    "14:10:31 - ⏳ Chờ coin... (5241)",
    "14:09:30 - ⏳ Chờ coin... (5241)",
    "14:08:29 - ⏳ Chờ coin... (5241)",
    "14:07:28 - ⏳ Chờ coin... (5241)",
    "14:06:27 - ⏳ Chờ coin... (5241)",
    "14:05:26 - ⏳ Chờ coin... (5241)",
    "14:04:25 - ⏳ Chờ coin... (5241)",
    "14:03:24 - ⏳ Chờ coin... (5241)",
    "14:02:23 - ⏳ Chờ coin... (5241)",
    "14:01:22 - ⏳ Chờ coin... (5241)",
    "14:00:21 - ⏳ Chờ coin... (5241)",
    "13:59:20 - ⏳ Chờ coin... (5241)",
    "13:58:19 - ⏳ Chờ coin... (5241)",
    "13:57:18 - ⏳ Chờ coin... (5241)",
    "13:56:17 - ⏳ Chờ coin... (5241)",
    "13:55:16 - ⏳ Chờ coin... (5241)",
    "13:54:15 - ⏳ Chờ coin... (5241)",
    "13:53:14 - ⏳ Chờ coin... (5241)",
    "13:52:13 - ⏳ Chờ coin... (5241)",
    "13:51:13 - ⏳ Chờ coin... (5241)",
    "13:50:12 - ⏳ Chờ coin... (5241)",
    "13:49:11 - ⏳ Chờ coin... (5241)",
    "13:48:10 - ⏳ Chờ coin... (5241)",
    "13:47:09 - ⏳ Chờ coin... (5241)",
    "13:46:08 - ⏳ Chờ coin... (5241)",
    "13:45:07 - ⏳ Chờ coin... (5241)",
    "13:44:06 - ⏳ Chờ coin... (5241)",
    "13:43:05 - ⏳ Chờ coin... (5241)",
    "13:42:04 - ⏳ Chờ coin... (5241)",
    "13:41:03 - ⏳ Chờ coin... (5241)",
    "13:40:02 - ⏳ Chờ coin... (5241)",
    "13:39:02 - ⏳ Chờ coin... (5241)",
    "13:38:01 - ⏳ Chờ coin... (5241)",
    "13:37:00 - ⏳ Chờ coin... (5241)",
    "13:35:59 - ⏳ Chờ coin... (5241)",
    "13:34:58 - ⏳ Chờ coin... (5241)",
    "13:33:57 - ⏳ Chờ coin... (5241)",
    "13:32:56 - ⏳ Chờ coin... (5241)",
    "13:31:55 - ⏳ Chờ coin... (5241)",
    "13:30:54 - ⏳ Chờ coin... (5241)"
  ]
}