{
  "total_coins": 1210,
  "start_coin": 1210,
  "coins_per_hour": 0.0,
  "coins_today": 0,
  "today_date": "2026-03-10",
  "last_updated": "2026-03-10 17:20:30",
  "logs": [
    "17:20:30 - ⏳ Chờ coin... (1210)",
    "17:19:29 - ⏳ Chờ coin... (1210)",
    "17:18:29 - ⏳ Chờ coin... (1210)",
    "17:17:28 - ⏳ Chờ coin... (1210)",
    "17:16:27 - ⏳ Chờ coin... (1210)",
    "17:15:26 - ⏳ Chờ coin... (1210)",
    "17:14:25 - ⏳ Chờ coin... (1210)",
    "17:13:25 - ⏳ Chờ coin... (1210)",
    "17:12:24 - ⏳ Chờ coin... (1210)",
    "17:11:23 - ⏳ Chờ coin... (1210)",
    "17:10:23 - ⏳ Chờ coin... (1210)",
    "17:09:21 - ⏳ Chờ coin... (1210)",
    "17:08:21 - ⏳ Chờ coin... (1210)",
    "17:07:20 - ⏳ Chờ coin... (1210)",
    "17:06:19 - ⏳ Chờ coin... (1210)",
    "17:05:18 - ⏳ Chờ coin... (1210)",
    "17:04:17 - ⏳ Chờ coin... (1210)",
    "17:03:17 - ⏳ Chờ coin... (1210)",
    "17:02:16 - ⏳ Chờ coin... (1210)",
    "17:01:15 - ⏳ Chờ coin... (1210)",
    "17:00:13 - ⏳ Chờ coin... (1210)",
    "16:59:12 - ⏳ Chờ coin... (1210)",
    "16:58:11 - ⏳ Chờ coin... (1210)",
    "16:57:11 - ⏳ Chờ coin... (1210)",
    "16:56:10 - ⏳ Chờ coin... (1210)",
    "16:55:09 - ⏳ Chờ coin... (1210)",
    "16:54:08 - ⏳ Chờ coin... (1210)",
    "16:53:07 - ⏳ Chờ coin... (1210)",
    "16:52:06 - ⏳ Chờ coin... (1210)",
    "16:51:06 - ⏳ Chờ coin... (1210)",
    "16:50:05 - ⏳ Chờ coin... (1210)",
    "16:49:04 - ⏳ Chờ coin... (1210)",
    "16:48:03 - ⏳ Chờ coin... (1210)",
    "16:47:02 - ⏳ Chờ coin... (1210)",
    "16:46:01 - ⏳ Chờ coin... (1210)",
    "16:45:01 - ⏳ Chờ coin... (1210)",
    "16:44:00 - ⏳ Chờ coin... (1210)",
    "16:42:59 - ⏳ Chờ coin... (1210)",
    "16:41:58 - ⏳ Chờ coin... (1210)",
    "16:40:57 - ⏳ Chờ coin... (1210)",
    "16:39:57 - ⏳ Chờ coin... (1210)",
    "16:38:56 - ⏳ Chờ coin... (1210)",
    "16:37:55 - ⏳ Chờ coin... (1210)",
    "16:36:55 - ⏳ Chờ coin... (1210)",
    "16:35:54 - ⏳ Chờ coin... (1210)",
    "16:34:53 - ⏳ Chờ coin... (1210)",
    "16:33:52 - ⏳ Chờ coin... (1210)",
    "16:32:51 - ⏳ Chờ coin... (1210)",
    "16:31:50 - ⏳ Chờ coin... (1210)",
    "16:30:49 - ⏳ Chờ coin... (1210)"
  ]
}