{
  "total_coins": 9904,
  "start_coin": 9904,
  "coins_per_hour": 0.0,
  "coins_today": 0,
  "today_date": "2026-04-02",
  "last_updated": "2026-04-02 11:17:43",
  "logs": [
    "11:17:43 - ⏳ Chờ coin... (9904)",
    "11:16:42 - ⏳ Chờ coin... (9904)",
    "11:15:41 - ⏳ Chờ coin... (9904)",
    "11:14:40 - ⏳ Chờ coin... (9904)",
    "11:13:40 - ⏳ Chờ coin... (9904)",
    "11:12:39 - ⏳ Chờ coin... (9904)",
    "11:11:38 - ⏳ Chờ coin... (9904)",
    "11:10:38 - ⏳ Chờ coin... (9904)",
    "11:09:37 - ⏳ Chờ coin... (9904)",
    "11:08:36 - ⏳ Chờ coin... (9904)",
    "11:07:36 - ⏳ Chờ coin... (9904)",
    "11:06:35 - ⏳ Chờ coin... (9904)",
    "11:05:34 - ⏳ Chờ coin... (9904)",
    "11:04:34 - ⏳ Chờ coin... (9904)",
    "11:03:33 - ⏳ Chờ coin... (9904)",
    "11:02:32 - ⏳ Chờ coin... (9904)",
    "11:01:32 - ⏳ Chờ coin... (9904)",
    "11:00:31 - ⏳ Chờ coin... (9904)",
    "10:59:30 - ⏳ Chờ coin... (9904)",
    "10:58:30 - ⏳ Chờ coin... (9904)",
    "10:57:29 - ⏳ Chờ coin... (9904)",
    "10:56:28 - ⏳ Chờ coin... (9904)",
    "10:55:28 - ⏳ Chờ coin... (9904)",
    "10:54:27 - ⏳ Chờ coin... (9904)",
    "10:53:26 - 🚀 Bắt đầu AFK | 💰 Coin: 9904",
    "10:52:02 - ⏳ Chờ coin... (9904)",
    "10:51:01 - ⏳ Chờ coin... (9904)",
    "10:50:00 - ⏳ Chờ coin... (9904)",
    "10:48:59 - ⏳ Chờ coin... (9904)",
    "10:47:58 - ⏳ Chờ coin... (9904)",
    "10:46:57 - ⏳ Chờ coin... (9904)",
    "10:45:56 - ⏳ Chờ coin... (9904)",
    "10:44:55 - ⏳ Chờ coin... (9904)",
    "10:43:54 - ⏳ Chờ coin... (9904)",
    "10:42:53 - ⏳ Chờ coin... (9904)",
    "10:41:52 - ⏳ Chờ coin... (9904)",
    "10:40:51 - ⏳ Chờ coin... (9904)",
    "10:39:50 - ⏳ Chờ coin... (9904)",
    "10:38:49 - ⏳ Chờ coin... (9904)",
    "10:37:48 - ⏳ Chờ coin... (9904)",
    "10:36:47 - ⏳ Chờ coin... (9904)",
    "10:35:46 - ⏳ Chờ coin... (9904)",
    "10:34:45 - ⏳ Chờ coin... (9904)",
    "10:33:44 - ⏳ Chờ coin... (9904)",
    "10:32:43 - ⏳ Chờ coin... (9904)",
    "10:31:42 - ⏳ Chờ coin... (9904)",
    "10:30:41 - ⏳ Chờ coin... (9904)",
    "10:29:40 - ⏳ Chờ coin... (9904)",
    "10:28:39 - ⏳ Chờ coin... (9904)",
    "10:27:38 - ⏳ Chờ coin... (9904)"
  ]
}