{
  "total_coins": 375,
  "start_coin": 375,
  "coins_per_hour": 0.0,
  "coins_today": 0,
  "today_date": "2026-03-09",
  "last_updated": "2026-03-09 06:54:31",
  "logs": [
    "06:54:31 - ⏳ Chờ coin... (375)",
    "06:53:30 - ⏳ Chờ coin... (375)",
    "06:52:30 - ⏳ Chờ coin... (375)",
    "06:51:29 - ⏳ Chờ coin... (375)",
    "06:50:28 - ⏳ Chờ coin... (375)",
    "06:49:28 - ⏳ Chờ coin... (375)",
    "06:48:27 - ⏳ Chờ coin... (375)",
    "06:47:26 - ⏳ Chờ coin... (375)",
    "06:46:26 - ⏳ Chờ coin... (375)",
    "06:45:25 - ⏳ Chờ coin... (375)",
    "06:44:24 - ⏳ Chờ coin... (375)",
    "06:43:24 - ⏳ Chờ coin... (375)",
    "06:42:23 - ⏳ Chờ coin... (375)",
    "06:41:22 - ⏳ Chờ coin... (375)",
    "06:40:22 - ⏳ Chờ coin... (375)",
    "06:39:21 - ⏳ Chờ coin... (375)",
    "06:38:20 - ⏳ Chờ coin... (375)",
    "06:37:20 - ⏳ Chờ coin... (375)",
    "06:36:19 - ⏳ Chờ coin... (375)",
    "06:35:18 - ⏳ Chờ coin... (375)",
    "06:34:18 - ⏳ Chờ coin... (375)",
    "06:33:17 - ⏳ Chờ coin... (375)",
    "06:32:16 - ⏳ Chờ coin... (375)",
    "06:31:16 - ⏳ Chờ coin... (375)",
    "06:30:15 - ⏳ Chờ coin... (375)",
    "06:29:14 - ⏳ Chờ coin... (375)",
    "06:28:14 - ⏳ Chờ coin... (375)",
    "06:27:13 - ⏳ Chờ coin... (375)",
    "06:26:12 - ⏳ Chờ coin... (375)",
    "06:25:12 - ⏳ Chờ coin... (375)",
    "06:24:11 - ⏳ Chờ coin... (375)",
    "06:23:10 - ⏳ Chờ coin... (375)",
    "06:22:10 - ⏳ Chờ coin... (375)",
    "06:21:09 - ⏳ Chờ coin... (375)",
    "06:20:08 - ⏳ Chờ coin... (375)",
    "06:19:07 - ⏳ Chờ coin... (375)",
    "06:18:07 - ⏳ Chờ coin... (375)",
    "06:17:06 - ⏳ Chờ coin... (375)",
    "06:16:05 - ⏳ Chờ coin... (375)",
    "06:15:05 - ⏳ Chờ coin... (375)",
    "06:14:04 - ⏳ Chờ coin... (375)",
    "06:13:03 - ⏳ Chờ coin... (375)",
    "06:12:02 - ⏳ Chờ coin... (375)",
    "06:11:02 - ⏳ Chờ coin... (375)",
    "06:10:01 - ⏳ Chờ coin... (375)",
    "06:09:00 - ⏳ Chờ coin... (375)",
    "06:08:00 - ⏳ Chờ coin... (375)",
    "06:06:59 - ⏳ Chờ coin... (375)",
    "06:05:58 - ⏳ Chờ coin... (375)",
    "06:04:58 - ⏳ Chờ coin... (375)"
  ]
}