{
  "total_coins": 12552,
  "start_coin": 12552,
  "coins_per_hour": 0.0,
  "coins_today": 0,
  "today_date": "2026-03-24",
  "last_updated": "2026-03-24 10:16:48",
  "logs": [
    "10:16:48 - ⏳ Chờ coin... (12552)",
    "10:15:47 - ⏳ Chờ coin... (12552)",
    "10:14:46 - ⏳ Chờ coin... (12552)",
    "10:13:45 - ⏳ Chờ coin... (12552)",
    "10:12:44 - ⏳ Chờ coin... (12552)",
    "10:11:43 - ⏳ Chờ coin... (12552)",
    "10:10:43 - ⏳ Chờ coin... (12552)",
    "10:09:42 - ⏳ Chờ coin... (12552)",
    "10:08:41 - ⏳ Chờ coin... (12552)",
    "10:07:40 - ⏳ Chờ coin... (12552)",
    "10:06:39 - ⏳ Chờ coin... (12552)",
    "10:05:38 - ⏳ Chờ coin... (12552)",
    "10:04:37 - ⏳ Chờ coin... (12552)",
    "10:03:36 - ⏳ Chờ coin... (12552)",
    "10:02:35 - ⏳ Chờ coin... (12552)",
    "10:01:34 - ⏳ Chờ coin... (12552)",
    "10:00:33 - ⏳ Chờ coin... (12552)",
    "09:59:32 - ⏳ Chờ coin... (12552)",
    "09:58:32 - ⏳ Chờ coin... (12552)",
    "09:57:31 - ⏳ Chờ coin... (12552)",
    "09:56:30 - ⏳ Chờ coin... (12552)",
    "09:55:29 - ⏳ Chờ coin... (12552)",
    "09:54:28 - ⏳ Chờ coin... (12552)",
    "09:53:27 - ⏳ Chờ coin... (12552)",
    "09:52:26 - ⏳ Chờ coin... (12552)",
    "09:51:25 - ⏳ Chờ coin... (12552)",
    "09:50:24 - ⏳ Chờ coin... (12552)",
    "09:49:23 - ⏳ Chờ coin... (12552)",
    "09:48:22 - ⏳ Chờ coin... (12552)",
    "09:47:20 - ⏳ Chờ coin... (12552)",
    "09:46:19 - ⏳ Chờ coin... (12552)",
    "09:45:18 - ⏳ Chờ coin... (12552)",
    "09:44:17 - ⏳ Chờ coin... (12552)",
    "09:43:16 - ⏳ Chờ coin... (12552)",
    "09:42:15 - ⏳ Chờ coin... (12552)",
    "09:41:14 - ⏳ Chờ coin... (12552)",
    "09:40:13 - ⏳ Chờ coin... (12552)",
    "09:39:12 - ⏳ Chờ coin... (12552)",
    "09:38:12 - ⏳ Chờ coin... (12552)",
    "09:37:10 - ⏳ Chờ coin... (12552)",
    "09:36:10 - ⏳ Chờ coin... (12552)",
    "09:35:09 - ⏳ Chờ coin... (12552)",
    "09:34:08 - ⏳ Chờ coin... (12552)",
    "09:33:07 - ⏳ Chờ coin... (12552)",
    "09:32:06 - ⏳ Chờ coin... (12552)",
    "09:31:05 - ⏳ Chờ coin... (12552)",
    "09:30:03 - ⏳ Chờ coin... (12552)",
    "09:29:03 - ⏳ Chờ coin... (12552)",
    "09:28:02 - ⏳ Chờ coin... (12552)",
    "09:27:01 - ⏳ Chờ coin... (12552)"
  ]
}